gwap_framework
