Metadata-Version: 2.1
Name: gwap-framework
Version: 0.0.81
Summary: Biblioteca padrão de framework para aplicações em Python no GWAP.
Home-page: https://gitlab.com/gwap/python/gwap-framework/
Author: Guilherme Dalmarco
Author-email: dalmarco.br@gmail.com
License: UNKNOWN
Platform: any
Classifier: Development Status :: 2 - Pre-Alpha
Classifier: Programming Language :: Python :: 3.7
Classifier: Topic :: Software Development
Classifier: Topic :: Utilities
